Workbook

Sheet Summary
A1: PAYFINIA — MIGRATION ROI: HEADLINE RESULTS
A2: Annual financial impact of migrating legacy volume to instant rails (full-cost model, v2).
A4: Result | B4: Small CFI | C4: Mid CFI | D4: Large CFI
A5: Net annual benefit | B5: ='ROI Model'!B21 -> 42900 | C5: ='ROI Model'!C21 -> 305805 | D5: ='ROI Model'!D21 -> 1656600
A6: Gross annual savings | B6: ='ROI Model'!B19 -> 72900 | C6: ='ROI Model'!C19 -> 365805 | D6: ='ROI Model'!D19 -> 1806600
A7: Year-1 ROI | B7: ='ROI Model'!B24 -> 0.715 | C7: ='ROI Model'!C24 -> 2.0387 | D7: ='ROI Model'!D24 -> 4.7331429
A8: Payback (months) | B8: ='ROI Model'!B25 -> 16.783217 | C8: ='ROI Model'!C25 -> 5.8861039 | D8: ='ROI Model'!D25 -> 2.5353133
A9: 5-year NPV | B9: ='ROI Model'!B26 -> 102624.75 | C9: ='ROI Model'!C26 -> 1009241.5 | D9: ='ROI Model'!D26 -> 5929817.4
A11: Full-cost model (8 components/rail + fixed costs). Illustrative until calibrated with Payfinia data. See Methodology & Sources tabs.

Sheet Assumptions
A1: ASSUMPTIONS — full cost stack (blue = editable inputs)
A2: Every rail's fully-loaded cost is built from 8 components. Change any blue cell and all results update. Sources on the 'Sources' tab.
A4: Cost component ($/txn) | B4: Check | C4: Wire | D4: Same-Day ACH | E4: ACH | F4: Instant
A5: 1. Network fee | B5: 0.03 | C5: 0.82 | D5: 0.05 | E5: 0.005 | F5: 0.045
A6: 2. Processing / operations | B6: 2 | C6: 12 | D6: 0.8 | E6: 0.15 | F6: 0.1
A7: 3a. Failure/return rate (%) | B7: 0.015 | C7: 0.01 | D7: 0.015 | E7: 0.015 | F7: 0.005
A8: 3b. Cost per failed item | B8: 8 | C8: 25 | D8: 6 | E8: 4 | F8: 5
A9: 3. Failure & exception cost | B9: =B7*B8 -> 0.12 | C9: =C7*C8 -> 0.25 | D9: =D7*D8 -> 0.09 | E9: =E7*E8 -> 0.06 | F9: =F7*F8 -> 0.025
A10: 4. Fraud loss (expected) | B10: 0.4 | C10: 2 | D10: 0.15 | E10: 0.05 | F10: 0.25
A11: 5. Fraud prevention / screening | B11: 0.1 | C11: 1 | D11: 0.1 | E11: 0.05 | F11: 0.15
A12: 6. Compliance (AML/sanctions) | B12: 0.03 | C12: 2 | D12: 0.05 | E12: 0.03 | F12: 0.1
A13: 7. Reconciliation | B13: 0.3 | C13: 0.5 | D13: 0.1 | E13: 0.05 | F13: 0.05
A14: 8. Liquidity / prefunding | B14: 0 | C14: 0 | D14: 0 | E14: 0 | F14: 0.05
A15: TOTAL cost per transaction | B15: =B5+B6+B9+B10+B11+B12+B13+B14 -> 2.98 | C15: =C5+C6+C9+C10+C11+C12+C13+C14 -> 18.57 | D15: =D5+D6+D9+D10+D11+D12+D13+D14 -> 1.34 | E15: =E5+E6+E9+E10+E11+E12+E13+E14 -> 0.395 | F15: =F5+F6+F9+F10+F11+F12+F13+F14 -> 0.77
A17: Substitution % (legacy→instant) | B17: 0.25 | C17: 0.3 | D17: 0.2 | E17: 0.05 | F17: n/a
A19: Discount rate (NPV) | B19: 0.1
A20: Horizon (years) | B20: 5
A22: Note:
A23: Instant is NOT free: its fraud loss, real-time screening and prefunding push its full cost to ~$0.77/txn. Because standard ACH already costs less than that, migrating ACH shows a NEGATIVE saving — an honest result. The ROI is driven by checks and wires.

Sheet CFI Profiles
A1: CFI PROFILES (blue = inputs — replace with a real prospect)
A2: Annual transaction volumes by legacy rail + institution-specific one-time and annual fixed costs.
A4: CFI | B4: Assets | C4: Members | D4: Check vol | E4: Wire vol | F4: Same-Day ACH vol | G4: ACH vol | H4: One-time cost | I4: Annual fixed cost
A5: Small CFI | B5: $200M | C5: 15000 | D5: 120000 | E5: 2000 | F5: 30000 | G5: 400000 | H5: 60000 | I5: 30000
A6: Mid CFI | B6: $1B | C6: 75000 | D6: 600000 | E6: 12000 | F6: 150000 | G6: 2500000 | H6: 150000 | I6: 60000
A7: Large CFI | B7: $5B | C7: 350000 | D7: 3000000 | E7: 60000 | F7: 800000 | G7: 14000000 | H7: 350000 | I7: 150000

Sheet ROI Model
A1: MIGRATION ROI MODEL (v2)
A2: Live formulas linked to Assumptions and CFI Profiles. Negative ACH saving is expected (ACH already cheaper than instant).
A4: Metric | B4: Small CFI | C4: Mid CFI | D4: Large CFI
A5: Migrated Check volume | B5: ='CFI Profiles'!D5*Assumptions!$B$17 -> 30000 | C5: ='CFI Profiles'!D6*Assumptions!$B$17 -> 150000 | D5: ='CFI Profiles'!D7*Assumptions!$B$17 -> 750000
A6: Migrated Wire volume | B6: ='CFI Profiles'!E5*Assumptions!$C$17 -> 600 | C6: ='CFI Profiles'!E6*Assumptions!$C$17 -> 3600 | D6: ='CFI Profiles'!E7*Assumptions!$C$17 -> 18000
A7: Migrated Same-Day ACH volume | B7: ='CFI Profiles'!F5*Assumptions!$D$17 -> 6000 | C7: ='CFI Profiles'!F6*Assumptions!$D$17 -> 30000 | D7: ='CFI Profiles'!F7*Assumptions!$D$17 -> 160000
A8: Migrated ACH volume | B8: ='CFI Profiles'!G5*Assumptions!$E$17 -> 20000 | C8: ='CFI Profiles'!G6*Assumptions!$E$17 -> 125000 | D8: ='CFI Profiles'!G7*Assumptions!$E$17 -> 700000
A10: Savings per txn — Check | B10: =Assumptions!$B$15-Assumptions!$F$15 -> 2.21 | C10: =Assumptions!$B$15-Assumptions!$F$15 -> 2.21 | D10: =Assumptions!$B$15-Assumptions!$F$15 -> 2.21
A11: Savings per txn — Wire | B11: =Assumptions!$C$15-Assumptions!$F$15 -> 17.8 | C11: =Assumptions!$C$15-Assumptions!$F$15 -> 17.8 | D11: =Assumptions!$C$15-Assumptions!$F$15 -> 17.8
A12: Savings per txn — Same-Day ACH | B12: =Assumptions!$D$15-Assumptions!$F$15 -> 0.57 | C12: =Assumptions!$D$15-Assumptions!$F$15 -> 0.57 | D12: =Assumptions!$D$15-Assumptions!$F$15 -> 0.57
A13: Savings per txn — ACH | B13: =Assumptions!$E$15-Assumptions!$F$15 -> -0.375 | C13: =Assumptions!$E$15-Assumptions!$F$15 -> -0.375 | D13: =Assumptions!$E$15-Assumptions!$F$15 -> -0.375
A15: Annual savings — Check | B15: =B5*B10 -> 66300 | C15: =C5*C10 -> 331500 | D15: =D5*D10 -> 1657500
A16: Annual savings — Wire | B16: =B6*B11 -> 10680 | C16: =C6*C11 -> 64080 | D16: =D6*D11 -> 320400
A17: Annual savings — Same-Day ACH | B17: =B7*B12 -> 3420 | C17: =C7*C12 -> 17100 | D17: =D7*D12 -> 91200
A18: Annual savings — ACH | B18: =B8*B13 -> -7500 | C18: =C8*C13 -> -46875 | D18: =D8*D13 -> -262500
A19: GROSS annual savings | B19: =SUM(B15:B18) -> 72900 | C19: =SUM(C15:C18) -> 365805 | D19: =SUM(D15:D18) -> 1806600
A20: Less: annual fixed cost | B20: ='CFI Profiles'!I5 -> 30000 | C20: ='CFI Profiles'!I6 -> 60000 | D20: ='CFI Profiles'!I7 -> 150000
A21: NET annual benefit | B21: =B19-B20 -> 42900 | C21: =C19-C20 -> 305805 | D21: =D19-D20 -> 1656600
A22: One-time cost | B22: ='CFI Profiles'!H5 -> 60000 | C22: ='CFI Profiles'!H6 -> 150000 | D22: ='CFI Profiles'!H7 -> 350000
A24: Year-1 ROI | B24: =B21/B22 -> 0.715 | C24: =C21/C22 -> 2.0387 | D24: =D21/D22 -> 4.7331429
A25: Payback period (months) | B25: =B22/B21*12 -> 16.783217 | C25: =C22/C21*12 -> 5.8861039 | D25: =D22/D21*12 -> 2.5353133
A26: 5-year NPV | B26: =B21*((1-(1+Assumptions!$B$19)^(-Assumptions!$B$20))/Assumptions!$B$19)-B22 -> 102624.75 | C26: =C21*((1-(1+Assumptions!$B$19)^(-Assumptions!$B$20))/Assumptions!$B$19)-C22 -> 1009241.5 | D26: =D21*((1-(1+Assumptions!$B$19)^(-Assumptions!$B$20))/Assumptions!$B$19)-D22 -> 5929817.4

Sheet Sensitivity
A1: SENSITIVITY ANALYSIS (Mid CFI)
A2: Which input moves ROI most? Two one-way sensitivities on the Mid CFI.
A4: 1) Substitution-rate multiplier
A5: Multiplier | B5: Net annual benefit | C5: Year-1 ROI
A6: 0.5 | B6: ='ROI Model'!C19*A6-'ROI Model'!C20 -> 122902.5 | C6: =B6/'ROI Model'!C22 -> 0.81935
A7: 0.75 | B7: ='ROI Model'!C19*A7-'ROI Model'!C20 -> 214353.75 | C7: =B7/'ROI Model'!C22 -> 1.429025
A8: 1 | B8: ='ROI Model'!C19*A8-'ROI Model'!C20 -> 305805 | C8: =B8/'ROI Model'!C22 -> 2.0387
A9: 1.25 | B9: ='ROI Model'!C19*A9-'ROI Model'!C20 -> 397256.25 | C9: =B9/'ROI Model'!C22 -> 2.648375
A10: 1.5 | B10: ='ROI Model'!C19*A10-'ROI Model'!C20 -> 488707.5 | C10: =B10/'ROI Model'!C22 -> 3.25805
A13: 2) Instant fully-loaded cost ($/txn)
A14: Instant cost | B14: Net annual benefit | C14: Year-1 ROI
A15: 0.5 | B15: =('ROI Model'!C19+(Assumptions!$F$15-A15)*('ROI Model'!C5+'ROI Model'!C6+'ROI Model'!C7+'ROI Model'!C8))-'ROI Model'!C20 -> 389127 | C15: =B15/'ROI Model'!C22 -> 2.59418
A16: 0.77 | B16: =('ROI Model'!C19+(Assumptions!$F$15-A16)*('ROI Model'!C5+'ROI Model'!C6+'ROI Model'!C7+'ROI Model'!C8))-'ROI Model'!C20 -> 305805 | C16: =B16/'ROI Model'!C22 -> 2.0387
A17: 1 | B17: =('ROI Model'!C19+(Assumptions!$F$15-A17)*('ROI Model'!C5+'ROI Model'!C6+'ROI Model'!C7+'ROI Model'!C8))-'ROI Model'!C20 -> 234827 | C17: =B17/'ROI Model'!C22 -> 1.5655133
A18: 1.5 | B18: =('ROI Model'!C19+(Assumptions!$F$15-A18)*('ROI Model'!C5+'ROI Model'!C6+'ROI Model'!C7+'ROI Model'!C8))-'ROI Model'!C20 -> 80527 | C18: =B18/'ROI Model'!C22 -> 0.53684667
A19: 2 | B19: =('ROI Model'!C19+(Assumptions!$F$15-A19)*('ROI Model'!C5+'ROI Model'!C6+'ROI Model'!C7+'ROI Model'!C8))-'ROI Model'!C20 -> -73773 | C19: =B19/'ROI Model'!C22 -> -0.49182
A21: Takeaway:
A22: ROI is most sensitive to (1) how much check & wire volume migrates and (2) the true fully-loaded cost of instant. If instant costs ~$2/txn, migration stops paying. These are the parameters to calibrate with Payfinia production data.

Sheet Methodology
A1: METHODOLOGY (v2 — detailed cost model)
A3: The cost stack — 8 components per transaction (Assumptions tab)
A4: 1 Network fee · 2 Processing/labor · 3 Failure & exception (return rate x cost per failed item) · 4 Fraud loss · 5 Fraud prevention/screening · 6 Compliance (AML/sanctions) · 7 Reconciliation · 8 Liquidity/prefunding.
A5: Fully-loaded cost per rail = the sum of these eight. Instant carries real fraud, screening, and prefunding costs, so it is ~$0.77/txn — not free.
A7: How the ROI is built (4 steps)
A8: 1 SUBSTITUTION: only a share of each legacy rail's volume migrates (never 100%).
A9: 2 SAVINGS/TXN: legacy fully-loaded cost minus instant fully-loaded cost. This is NEGATIVE for standard ACH.
A10: 3 ANNUAL: migrated volume x savings per txn, summed across rails = gross savings. Minus annual fixed cost = net benefit.
A11: 4 RETURNS: ROI = net benefit / one-time cost; payback = one-time / net; NPV discounts 5 years of net benefit at 10% minus the one-time cost.
A13: Why it is defensible now
A14: Every cost line is itemized, sourced, and adjustable. The model no longer treats instant as free, includes failure/exception and compliance/liquidity costs, and honestly shows ACH migration as a cost — so a financially-literate prospect can audit it.
A16: Calibrate these with Payfinia production data
A17: Fraud loss & prevention per item · true processing/labor per item · failure/return rates · compliance and liquidity carrying cost · real substitution rates.

Sheet Sources
A1: SOURCES — benchmark basis for each cost line
A3: Cost component | B3: Benchmark basis | C3: Source
A4: Network fee | B4: Fedwire ~$0.82; FedNow/RTP $0.045; ACH fractions of a cent | C4: Fed / Nacha / TCH pricing (Deliverable 1)
A5: Processing / labor | B5: Manual handling for checks/wires; automated for ACH/instant | C5: Industry op-cost estimates (Deliverable 1)
A6: Failure & exception | B6: Return rates ~1.5% overall (Nacha thresholds); return fees $2-$5; avg failed B2B payment $12.10 | C6: Nacha; LexisNexis / industry
A7: Fraud loss | B7: 2024 losses: check ~$24B, ACH ~$11B, APP ~$12.5B; instant irrevocable | C7: AFP Fraud Survey; iPiD; industry
A8: Fraud prevention | B8: Real-time screening/monitoring tooling per item | C8: Industry (fraud-prevention vendors)
A9: Compliance | B9: AML / OFAC sanctions screening per item; mandatory on wires | C9: FFIEC; BSA/AML guidance
A10: Reconciliation | B10: Matching & breaks handling; heavier for paper rails | C10: Exception-management research
A11: Liquidity / prefunding | B11: RTP prefunded joint account at FRBNY; FedNow liquidity mgmt | C11: frbservices.org (Deliverable 1)
A14: Note: dollar figures are conservative public-benchmark midpoints. Replace with Payfinia production data during calibration.
